{
    "CLI_version": "7.6.3",
    "branch": "master",
    "certora_ci_client": null,
    "conf": {
        "files": [
            "Empty.sol"
        ],
        "process": "emv",
        "rule": [
            "sistersBirthMonths"
        ],
        "verify": "Empty:sisters.spec"
    },
    "conf_path": null,
    "cwd_relative": "task",
    "dirty": true,
    "main_spec": "sisters.spec",
    "origin": "git@github.com:ShoshiSternberg/labs.git",
    "raw_args": [
        "/home/user/.local/bin/certoraRun",
        "Empty.sol",
        "--verify",
        "Empty:sisters.spec",
        "--rule",
        "sistersBirthMonths"
    ],
    "revision": "5a24bee5b4437120aaf300aae1460c89151b682d",
    "timestamp": "1716112884.518611"
}